orion/__init__.py
orion/backend/__init__.py
orion/backend/heaan/README.md
orion/backend/lattigo/__init__.py
orion/backend/lattigo/bindings.py
orion/backend/lattigo/bootstrapper.go
orion/backend/lattigo/encoder.go
orion/backend/lattigo/encryptor.go
orion/backend/lattigo/evaluator.go
orion/backend/lattigo/go.mod
orion/backend/lattigo/go.sum
orion/backend/lattigo/keygenerator.go
orion/backend/lattigo/lineartransform.go
orion/backend/lattigo/main.go
orion/backend/lattigo/minheap.go
orion/backend/lattigo/polyeval.go
orion/backend/lattigo/scheme.go
orion/backend/lattigo/tensors.go
orion/backend/lattigo/utils.go
orion/backend/openfhe/README.md
orion/backend/python/__init__.py
orion/backend/python/bootstrapper.py
orion/backend/python/encoder.py
orion/backend/python/encryptor.py
orion/backend/python/evaluator.py
orion/backend/python/key_generator.py
orion/backend/python/lt_evaluator.py
orion/backend/python/parameters.py
orion/backend/python/poly_evaluator.py
orion/backend/python/tensors.py
orion/core/__init__.py
orion/core/auto_bootstrap.py
orion/core/fuser.py
orion/core/level_dag.py
orion/core/network_dag.py
orion/core/orion.py
orion/core/packing.py
orion/core/tracer.py
orion/core/utils.py
orion/models/__init__.py
orion/models/alexnet.py
orion/models/lenet.py
orion/models/lola.py
orion/models/mlp.py
orion/models/resnet.py
orion/models/vgg.py
orion/models/yolo.py
orion/nn/__init__.py
orion/nn/activation.py
orion/nn/linear.py
orion/nn/module.py
orion/nn/normalization.py
orion/nn/operations.py
orion/nn/pooling.py
orion/nn/reshape.py
orion/backend/lattigo/lattigo-mac-arm64.dylib
orion/backend/lattigo/lattigo-mac-arm64.h
orion_fhe-1.0.2.dist-info/LICENSE
orion_fhe-1.0.2.dist-info/METADATA
orion_fhe-1.0.2.dist-info/WHEEL
orion_fhe-1.0.2.dist-info/RECORD
