Metadata-Version: 2.3
Name: orion-fhe
Version: 1.0.2
Summary: A Fully Homomorphic Encryption Framework for Deep Learning
Author: Austin Ebel
Author-email: abe5240@nyu.edu
Requires-Python: >=3.9,<3.13
Classifier: Programming Language :: Python :: 3
Classifier: Programming Language :: Python :: 3.9
Classifier: Programming Language :: Python :: 3.10
Classifier: Programming Language :: Python :: 3.11
Classifier: Programming Language :: Python :: 3.12
Requires-Dist: PyYAML (>=6.0)
Requires-Dist: certifi (>=2024.2.2)
Requires-Dist: h5py (>=3.5.0)
Requires-Dist: matplotlib (>=3.1.0)
Requires-Dist: numpy (>=1.21.0)
Requires-Dist: scipy (>=1.7.0,<=1.14.1)
Requires-Dist: torch (>=2.2.0)
Requires-Dist: torchvision (>=0.17.0)
Requires-Dist: tqdm (>=4.30.0)
